LICENSE
MANIFEST.in
README.md
setup.py
NeoPySwitch/__init__.py
NeoPySwitch/pyswitch.py
NeoPySwitch.egg-info/PKG-INFO
NeoPySwitch.egg-info/SOURCES.txt
NeoPySwitch.egg-info/dependency_links.txt
NeoPySwitch.egg-info/top_level.txt