Metadata-Version: 1.1
Name: NeoPySwitch
Version: 0.2.1
Summary: Python switch implementation
Home-page: https://github.com/thomafred/NeoPySwitch
Author: Thomas Li Fredriksen
Author-email: tom@lifredriksen.no
License: MIT
Platform: UNKNOWN
Classifier: Development Status :: 3 - Alpha
Classifier: Intended Audience :: Developers
Classifier: License :: OSI Approved :: MIT License
Classifier: Programming Language :: Python
Classifier: Topic :: Software Development
Classifier: Programming Language :: Python :: 2.4
Classifier: Programming Language :: Python :: 2.5
Classifier: Programming Language :: Python :: 2.6
Classifier: Programming Language :: Python :: 2.7
Classifier: Programming Language :: Python :: 3.3
Classifier: Programming Language :: Python :: 3.4
Classifier: Programming Language :: Python :: 3.5
Provides: NeoPySwitch
